poept/__init__.py
poept/poept.py
PoePT-0.1.2.dist-info/METADATA
PoePT-0.1.2.dist-info/WHEEL
PoePT-0.1.2.dist-info/top_level.txt
PoePT-0.1.2.dist-info/RECORD
