Metadata-Version: 2.1
Name: PoePT
Version: 0.1.2
Summary: Python package for interacting with the POE chatbot
Home-page: https://github.com/saikyo0/PoePT
Author: Saikyo0
Author-email: mamaexus@gmail.com
Classifier: Development Status :: 3 - Alpha
Classifier: Intended Audience :: Developers
Classifier: License :: OSI Approved :: MIT License
Classifier: Programming Language :: Python :: 3
Classifier: Programming Language :: Python :: 3.6
Classifier: Programming Language :: Python :: 3.7
Classifier: Programming Language :: Python :: 3.8
Classifier: Programming Language :: Python :: 3.9
Requires-Dist: selenium
Requires-Dist: webdriver-manager
